[
  {
    "name": "Christopher Dziomba",
    "company": "Deutsche Telekom AG",
    "irc": null,
    "asn": "3320"
  },
  {
    "name": "Claudia Uhlich",
    "company": "Deutsche Telekom AG",
    "irc": null,
    "asn": "3320"
  },
  {
    "name": "Florian Mai",
    "company": "sipgate GmbH",
    "irc": null,
    "asn": "15594"
  },
  {
    "name": "Janina Faßbender",
    "company": "DENOG e.V. / DTAG",
    "irc": null,
    "asn": "3320"
  },
  {
    "name": "Jan Mußmann",
    "company": "UPONU GmbH",
    "irc": null,
    "asn": "208500"
  },
  {
    "name": "Jonas Böttner",
    "company": "sipgate GmbH",
    "irc": null,
    "asn": "15594"
  },
  {
    "name": "Marc Peters",
    "company": null,
    "irc": "mapet",
    "asn": null
  },
  {
    "name": "Peter Hansen",
    "company": "myLoc",
    "irc": null,
    "asn": "24961"
  },
  {
    "name": "Robert Dahlhoff",
    "company": "Deutsche Telekom AG",
    "irc": null,
    "asn": "3320"
  },
  {
    "name": "Rudolph Bott",
    "company": "sipgate GmbH / netzquadrat GmbH",
    "irc": "rbott",
    "asn": "15594"
  },
  {
    "name": "Sascha Hoppe",
    "company": null,
    "irc": "Kn0rki",
    "asn": null
  },
  {
    "name": "Sebastian Becker",
    "company": "DENOG e.V. / DTAG",
    "irc": "_sb_",
    "asn": "3320"
  },
  {
    "name": "Tarranum Kamal",
    "company": "Akamai Technologies",
    "irc": null,
    "asn": "20940"
  }
]
